regify/__init__.py
regify/core.py
regify/decorators.py
regify/manager.py
regify-0.2.0.dist-info/LICENSE
regify-0.2.0.dist-info/METADATA
regify-0.2.0.dist-info/WHEEL
regify-0.2.0.dist-info/RECORD
