Metadata-Version: 2.3
Name: regify
Version: 0.2.0
Summary: Thread-safe registry framework for Python objects, plugins, strategies, handlers, or any reusable objects.
Author: Ephraim Seddor
Author-email: seddorephraim7@gmail.com
Requires-Python: >=3.10,<3.14
Classifier: Programming Language :: Python :: 3
Classifier: Programming Language :: Python :: 3.10
Classifier: Programming Language :: Python :: 3.11
Classifier: Programming Language :: Python :: 3.12
Classifier: Programming Language :: Python :: 3.13
